deargui.cpython-36m-darwin.so
deargui-0.1.5.dist-info/METADATA
deargui-0.1.5.dist-info/RECORD
deargui-0.1.5.dist-info/WHEEL
deargui-0.1.5.dist-info/top_level.txt
