Metadata-Version: 1.0
Name: deargui
Version: 0.1.5
Summary: Python bindings for Dear ImGui
Home-page: http://github.com/cammm/deargui
Author: cammm
Author-email: UNKNOWN
License: MIT
Platform: UNKNOWN
